iflow_mcp_malloryai_mallory_mcp_server-0.1.0.dist-info/licenses/LICENSE.md
malloryai/mcp/__init__.py
malloryai/mcp/app.py
iflow_mcp_malloryai_mallory_mcp_server-0.1.0.dist-info/METADATA
iflow_mcp_malloryai_mallory_mcp_server-0.1.0.dist-info/WHEEL
iflow_mcp_malloryai_mallory_mcp_server-0.1.0.dist-info/entry_points.txt
iflow_mcp_malloryai_mallory_mcp_server-0.1.0.dist-info/top_level.txt
iflow_mcp_malloryai_mallory_mcp_server-0.1.0.dist-info/RECORD
