Metadata-Version: 2.4
Name: iflow-mcp_malloryai_mallory-mcp-server
Version: 0.1.0
Summary: MalloryAI Intelligence MCP Server
Author-email: Mallory Team <hello@mallory.ai>
License: MIT
Project-URL: Homepage, https://github.com/malloryai/mallory-mcp-server
Project-URL: Documentation, https://github.com/malloryai/mallory-mcp-server#readme
Project-URL: Repository, https://github.com/malloryai/mallory-mcp-server.git
Project-URL: Issues, https://github.com/malloryai/mallory-mcp-server/issues
Requires-Python: >=3.11
License-File: LICENSE.md
Requires-Dist: malloryai-sdk>=0.3.2
Requires-Dist: python-dotenv>=1.1.0
Requires-Dist: pydantic>=2.11.0
Requires-Dist: mcp[cli]>=1.6.0
Provides-Extra: lint
Requires-Dist: black>=24.10.0; extra == "lint"
Requires-Dist: isort>=5.13.2; extra == "lint"
Requires-Dist: flake8>=7.1.1; extra == "lint"
Provides-Extra: tools
Requires-Dist: bandit>=1.8.2; extra == "tools"
Requires-Dist: pre-commit>=4.1.0; extra == "tools"
Dynamic: license-file
